<?xml version="1.0" encoding="ISO-8859-1"?><!DOCTYPE ihtsoa SYSTEM "http://gisla-pn2.ip.tdk.dk/ihtsoa/ihtsoaWholeSale.dtd"><ihtsoa operation="get_accesspoint"> <header  userid="lwe"  useremail="lawe@tdc.dk"  trackingid="poster_20170404105124"  versionid="1.0"  companyid="TDC"  forceresult="1"  replytimestamp="2017-04-08 11:01:12"  statuscode="0"  statusmessage="No complications occured"  transactionduration="3.321315"  serverid="gisla-pn2.ip.tdk.dk" /> <get_accesspoint_request lid="TG300006"/> <get_accesspoint_response>  <customer   name="Dev OSST Test"   address1="Aarhus"   address2=""   zip="8000"   city="Århus C"  />  <accesspoint   lid="TG300006"   dslam="aptxda24"   port="1"   access_type="POTS"   platform="ETH"   line_speed_up="256"   line_speed_down="512"   best_effort="0"   shared_access="0"   modem_type=""   hgw_backdoor_ip="87.57.3.130"   hgw_backdoor_ip_v6=""   service_code="DEFAULT"   vectoring=""   ginp="Auto"   dlm_allowed="0"   ts_up_speed=""   ts_down_speed=""   actualcpetype=""   vectfallbackstate=""  >   <links>    <link     sequence_no="0"     lik="TG300006"     logical_port="1"     physical_port="1/1/1/1"    >     <lineinfo      current_up=""      current_down=""      margin_up=""      margin_down=""      attenuation_up=""      attenuation_down=""      attenuation_up_150khz=""      shaping=""      link_state=""      card_state=""      test_speed_active="0"     >      <cardinfo       cardtype=""       attainable_up=""       attainable_down=""       if_last_change=""       sys_up_time=""       actual_annex=""       annex_type=""      >       <possible_annexes/>      </cardinfo>     </lineinfo>    </link>   </links>   <channels>    <channel     channel_id="TG300006"     multi_service="0"     tp_no="6"     tp_descr="TP6 - Internet DHCP"     closed="0"     up_speed="256"     down_speed="512"     ip_qos="tdc:0-0-0"     uni_vpi="0"     uni_vci="101"     uni_vlan=""     outer_vlan="500"     mac_address_limit=""     comment="Oprettet i CU: 2016-10-21 17:49"     multicast="0"    >     <services>      <dsl_service       sik="TG300006"       service_type="Data"      />     </services>     <wans>      <wan       version="4"       prefix="87.57.3.130"       prefixlength="32"       no_of_ip="1"       ipaddresstype="P"      />      <wan       version="6"       prefix=""       prefixlength=""       no_of_ip=""       ipaddresstype=""      />     </wans>    </channel>   </channels>  </accesspoint> </get_accesspoint_response></ihtsoa>